sapien/__init__.py
sapien/__init__.pyi
sapien/_oidn_tricks.py
sapien/_vulkan_tricks.py
sapien/pysapien.cpython-310-x86_64-linux-gnu.so
sapien/pysapien_pinocchio.cpython-310-x86_64-linux-gnu.so
sapien/show_anything.py
sapien/version.py
sapien/asset/__init__.py
sapien/core/__init__.py
sapien/example/__init__.py
sapien/example/empty.py
sapien/example/hello_world.py
sapien/example/load_urdf.py
sapien/example/offscreen.py
sapien/include/dlpack/dlpack.h
sapien/include/glm/CMakeLists.txt
sapien/include/glm/common.hpp
sapien/include/glm/exponential.hpp
sapien/include/glm/ext.hpp
sapien/include/glm/fwd.hpp
sapien/include/glm/geometric.hpp
sapien/include/glm/glm.hpp
sapien/include/glm/integer.hpp
sapien/include/glm/mat2x2.hpp
sapien/include/glm/mat2x3.hpp
sapien/include/glm/mat2x4.hpp
sapien/include/glm/mat3x2.hpp
sapien/include/glm/mat3x3.hpp
sapien/include/glm/mat3x4.hpp
sapien/include/glm/mat4x2.hpp
sapien/include/glm/mat4x3.hpp
sapien/include/glm/mat4x4.hpp
sapien/include/glm/matrix.hpp
sapien/include/glm/packing.hpp
sapien/include/glm/trigonometric.hpp
sapien/include/glm/vec2.hpp
sapien/include/glm/vec3.hpp
sapien/include/glm/vec4.hpp
sapien/include/glm/vector_relational.hpp
sapien/include/glm/detail/_features.hpp
sapien/include/glm/detail/_fixes.hpp
sapien/include/glm/detail/_noise.hpp
sapien/include/glm/detail/_swizzle.hpp
sapien/include/glm/detail/_swizzle_func.hpp
sapien/include/glm/detail/_vectorize.hpp
sapien/include/glm/detail/compute_common.hpp
sapien/include/glm/detail/compute_vector_relational.hpp
sapien/include/glm/detail/func_common.inl
sapien/include/glm/detail/func_common_simd.inl
sapien/include/glm/detail/func_exponential.inl
sapien/include/glm/detail/func_exponential_simd.inl
sapien/include/glm/detail/func_geometric.inl
sapien/include/glm/detail/func_geometric_simd.inl
sapien/include/glm/detail/func_integer.inl
sapien/include/glm/detail/func_integer_simd.inl
sapien-3.0.2.dist-info/METADATA
sapien-3.0.2.dist-info/WHEEL
sapien-3.0.2.dist-info/top_level.txt
sapien-3.0.2.dist-info/RECORD
sapien-3.0.2.dist-info/licenses/LICENSE
