Metadata-Version: 2.1
Name: sapien
Version: 3.0.2
Summary: ['SAPIEN: A SimulAted Parted based Interactive ENvironment']
Home-page: https://sapien.ucsd.edu
Author: Sapien
Author-email: sapienaicontact@gmail.com
License: MIT
Project-URL: Documentation, https://sapien.ucsd.edu/docs
Keywords: robotics simulator dataset articulation partnet
Classifier: Operating System :: POSIX :: Linux
Classifier: Intended Audience :: Developers
Classifier: Intended Audience :: Education
Classifier: Intended Audience :: Other Audience
Classifier: Intended Audience :: Science/Research
Classifier: License :: OSI Approved :: MIT License
Classifier: Natural Language :: English
Classifier: Framework :: Robot Framework :: Tool
Classifier: Topic :: Games/Entertainment :: Simulation
Classifier: Programming Language :: C++
Classifier: Programming Language :: Python :: 3.8
Classifier: Programming Language :: Python :: 3.9
Classifier: Programming Language :: Python :: 3.10
Classifier: Programming Language :: Python :: 3.11
Classifier: Programming Language :: Python :: 3.12
Classifier: Topic :: Education
Classifier: Topic :: Software Development :: Libraries :: Python Modules
Classifier: Topic :: Utilities
Requires-Python: >=3.7
License-File: LICENSE
Requires-Dist: numpy>=1.17
Requires-Dist: requests>=2.22
Requires-Dist: transforms3d>=0.3
Requires-Dist: lxml
Requires-Dist: networkx
Requires-Dist: pyperclip
Requires-Dist: opencv-python>=4.0
Requires-Dist: setuptools
